iohxplainer/__init__.py
iohxplainer/core.py
iohxplainer/utils.py
iohxplainer-0.9.1.dist-info/LICENSE
iohxplainer-0.9.1.dist-info/METADATA
iohxplainer-0.9.1.dist-info/WHEEL
iohxplainer-0.9.1.dist-info/RECORD
